Metadata-Version: 2.1
Name: VHHHATISpy
Version: 1.0.0
Summary: Fetch ATIS data for Hong Kong International Airport.
Home-page: UNKNOWN
Author: William NG
Author-email: Williamntw.Website@gmail.com
License: UNKNOWN
Platform: UNKNOWN
Classifier: Programming Language :: Python :: 3
Classifier: License :: OSI Approved :: MIT License
Classifier: Operating System :: OS Independent
